{"cameraMode":{"drawMode":0,"name":"Shaded","section":"Shading Mode"},"sceneLighting":true,"audioPlay":false,"sceneViewState":{"m_AlwaysRefresh":false,"showFog":true,"showSkybox":true,"showFlares":true,"showImageEffects":true,"showParticleSystems":true,"showVisualEffectGraphs":true,"m_FxEnabled":true},"in2DMode":false,"pivot":{"x":22.83449935913086,"y":26.792814254760743,"z":-12.64022445678711},"rotation":{"x":0.10362157970666886,"y":-0.007151033729314804,"z":0.0007392650004476309,"w":0.9945970773696899},"size":21.47466278076172,"orthographic":false}